{
  "@context": {
    "@vocab": "https://bluebrain.github.io/nexus/vocabulary/",
    "resourceTypes": {
      "@type": "@id",
      "@container": "@set"
    },
    "projects": {
      "@container": "@list"
    },
    "identities": {
      "@container": "@set"
    },
    "subject": "https://bluebrain.github.io/nexus/vocabulary/subject",
    "_resolverId": {
      "@id": "https://bluebrain.github.io/nexus/vocabulary/resolverId",
      "@type": "@id"
    }
  },
  "@id": "https://bluebrain.github.io/nexus/contexts/resolver.json"
}